polars_statistics/__init__.py
polars_statistics/_polars_statistics.abi3.so
polars_statistics/exprs/__init__.py
polars_statistics/exprs/categorical.py
polars_statistics/exprs/correlation.py
polars_statistics/exprs/distributional.py
polars_statistics/exprs/forecast.py
polars_statistics/exprs/modern.py
polars_statistics/exprs/nonparametric.py
polars_statistics/exprs/parametric.py
polars_statistics/exprs/regression.py
polars_statistics/exprs/tost.py
polars_statistics/formula/__init__.py
polars_statistics/formula/expander.py
polars_statistics/formula/parser.py
polars_statistics/formula/terms.py
polars_statistics/models/__init__.py
polars_statistics-0.4.0.dist-info/METADATA
polars_statistics-0.4.0.dist-info/WHEEL
polars_statistics-0.4.0.dist-info/licenses/LICENSE
polars_statistics-0.4.0.dist-info/RECORD
