Metadata-Version: 2.4
Name: polars-statistics
Version: 0.4.0
Classifier: Development Status :: 4 - Beta
Classifier: Intended Audience :: Developers
Classifier: Intended Audience :: Science/Research
Classifier: License :: OSI Approved :: MIT License
Classifier: Operating System :: OS Independent
Classifier: Programming Language :: Python :: 3
Classifier: Programming Language :: Python :: 3.9
Classifier: Programming Language :: Python :: 3.10
Classifier: Programming Language :: Python :: 3.11
Classifier: Programming Language :: Python :: 3.12
Classifier: Programming Language :: Python :: Implementation :: CPython
Classifier: Programming Language :: Rust
Classifier: Topic :: Scientific/Engineering
Classifier: Topic :: Scientific/Engineering :: Mathematics
Classifier: Topic :: Scientific/Engineering :: Information Analysis
Classifier: Typing :: Typed
Requires-Dist: polars>=1.0.0
Requires-Dist: numpy>=1.21 ; extra == 'all'
Requires-Dist: numpy>=1.21 ; extra == 'dev'
Requires-Dist: pytest>=7.0 ; extra == 'dev'
Requires-Dist: scipy>=1.10 ; extra == 'dev'
Requires-Dist: statsmodels>=0.14 ; extra == 'dev'
Requires-Dist: maturin>=1.7.4 ; extra == 'dev'
Requires-Dist: numpy>=1.21 ; extra == 'numpy'
Provides-Extra: all
Provides-Extra: dev
Provides-Extra: numpy
License-File: LICENSE
Summary: Statistical tests, regression, and machine learning for Polars - t-tests, ANOVA, chi-square, correlation, OLS, GLM, quantile regression, and more
Keywords: polars,polars-plugin,statistics,statistical-analysis,hypothesis-testing,t-test,chi-square,anova,mann-whitney,wilcoxon,fisher-exact,regression,linear-regression,logistic-regression,glm,ols,ridge-regression,elastic-net,quantile-regression,robust-regression,correlation,pearson,spearman,kendall,bootstrap,equivalence-testing,tost,effect-size,data-science,machine-learning,scikit-learn-alternative,scipy-alternative,statsmodels-alternative,rust,high-performance
Author-email: Simon Müller <sm@data-zoo.de>
Maintainer-email: Simon Müller <sm@data-zoo.de>
License: MIT
Requires-Python: >=3.9
Project-URL: Changelog, https://github.com/DataZooDE/polars-statistics/releases
Project-URL: Documentation, https://github.com/DataZooDE/polars-statistics#readme
Project-URL: Homepage, https://github.com/DataZooDE/polars-statistics
Project-URL: Issues, https://github.com/DataZooDE/polars-statistics/issues
Project-URL: Repository, https://github.com/DataZooDE/polars-statistics
